[
    {
        "slot": "1",
        "abilities": {
            "1": "Rending Strike",
            "2": "Rending Spin"
        }
    },
    {
        "slot": "2",
        "abilities": {
            "1": "Deadly Chop",
            "2": "Adrenaline Boost",
            "3": "Battle Rush",
            "4": "Internal Bleeding",
            "5": "Raging Blades"
        }
    },
    {
        "slot": "3",
        "abilities": {
            "1": "Whirlwind"
        }
    },
    {
        "slot": "4",
        "abilities": {
            "1": "Deep Cuts",
            "2": "Life Leech",
            "3": "Increased Defence",
            "4": "Aggressive Rush"
        }
    }
]